fastuaparser.py
fastuaparser-0.1.4.dist-info/LICENSE
fastuaparser-0.1.4.dist-info/WHEEL
fastuaparser-0.1.4.dist-info/METADATA
fastuaparser-0.1.4.dist-info/RECORD
