Metadata-Version: 2.1
Name: fastuaparser
Version: 0.1.4
Summary: A super-fast user agent string parser 
Keywords: user-agent,web,analytics
Author: Almar Klein
Requires-Python: >= 3.6
Requires-Dist: fastuaparser[lint,tests, docs] ; extra == "dev"
Requires-Dist: ruff ; extra == "lint"
Requires-Dist: pytest ; extra == "tests"
Project-URL: Homepage, https://github.com/almarklein/fastuaparser
Project-URL: Repository, https://github.com/almarklein/fastuaparser
Provides-Extra: dev
Provides-Extra: lint
Provides-Extra: tests
